smartcut/__init__.py
smartcut/__main__.py
smartcut/cut_video.py
smartcut/media_container.py
smartcut/media_utils.py
smartcut/misc_data.py
smartcut/nal_tools.py
smartcut/parse_h265.py
smartcut-1.7.dist-info/licenses/LICENSE
smartcut-1.7.dist-info/METADATA
smartcut-1.7.dist-info/WHEEL
smartcut-1.7.dist-info/entry_points.txt
smartcut-1.7.dist-info/top_level.txt
smartcut-1.7.dist-info/RECORD
