Metadata-Version: 2.4
Name: smartcut
Version: 1.7
Summary: CLI tool for efficient video cutting with minimal recoding
Author-email: Santtu Keskinen <santtu.keskinen@gmail.com>
Maintainer-email: Santtu Keskinen <santtu.keskinen@gmail.com>
License-Expression: MIT
Project-URL: Homepage, https://github.com/skeskinen/smartcut
Project-URL: Documentation, https://github.com/skeskinen/smartcut/blob/main/README.md
Project-URL: Repository, https://github.com/skeskinen/smartcut.git
Project-URL: Bug Tracker, https://github.com/skeskinen/smartcut/issues
Project-URL: Changelog, https://github.com/skeskinen/smartcut/blob/main/README.md#version-history
Project-URL: Commercial GUI, https://smartmediacutter.com
Keywords: video,cutting,editing,ffmpeg,smart-cut,lossless,frame-accurate,cli,video-processing
Classifier: Development Status :: 5 - Production/Stable
Classifier: Intended Audience :: End Users/Desktop
Classifier: Intended Audience :: Developers
Classifier: Topic :: Multimedia :: Video :: Conversion
Classifier: Programming Language :: Python :: 3
Classifier: Programming Language :: Python :: 3.11
Classifier: Programming Language :: Python :: 3.12
Classifier: Operating System :: OS Independent
Requires-Python: >=3.11
License-File: LICENSE
Requires-Dist: numpy
Requires-Dist: av==16.0.1
Requires-Dist: tqdm
Provides-Extra: test
Requires-Dist: ffmpeg-python; extra == "test"
Requires-Dist: soundfile; extra == "test"
Requires-Dist: scipy; extra == "test"
Requires-Dist: requests; extra == "test"
Requires-Dist: psutil; extra == "test"
Provides-Extra: dev
Requires-Dist: build; extra == "dev"
Requires-Dist: twine; extra == "dev"
Requires-Dist: pyinstaller; extra == "dev"
Dynamic: license-file
